{"guide_index.md":"92111b91","index.md":"2ebe977f","useasyncorder_index.md":"f5999904","useboolean_index.md":"c270901b","usecookiestate_index.md":"9faf520d","usecounter_index.md":"77543d6a","usedarkmode_index.md":"af113320","usedebounce_index.md":"a596917e","usedebouncefn_index.md":"2162c357","usedrop_index.md":"a4df3ffd","useeventemitter_index.md":"7ef22aa4","useeventlistener_index.md":"f5d23b97","useexternal_index.md":"2786e3e6","usefavicon_index.md":"ec038be0","usefetchs_index.md":"15f6caba","usefocuswithin_index.md":"a620040a","useformatresult_index.md":"610f1613","usefullscreen_index.md":"7f7db63b","usehover_index.md":"9fef7cc7","useinviewport_index.md":"d546dbba","useinfinitescroll_index.md":"5fc971ca","useinterval_index.md":"c2a26384","usekeypress_index.md":"66ae2cc1","uselocalstoragestate_index.md":"88df5abd","uselockfn_index.md":"d8fde3a7","usemap_index.md":"ee08b0af","usemedia_index.md":"780b7c5a","usemouse_index.md":"1a399213","usenetwork_index.md":"3a726d24","usepreview_index.md":"0159e359","userequest_basic_index.md":"7da11c00","userequest_cache_index.md":"60e25ef8","userequest_debounce_index.md":"b89fac1d","userequest_fetchs_index.md":"dcf6aa31","userequest_guide_index.md":"69489b5a","userequest_index.md":"99dde1f6","userequest_loadingdelay_index.md":"0dc6995f","userequest_plugin_index.md":"69d11e14","userequest_polling_index.md":"d74cd3f8","userequest_ready_index.md":"7912c56e","userequest_refreshdeps_index.md":"9c4acb22","userequest_refreshonwindowfocus_index.md":"f25fe3d1","userequest_retry_index.md":"f15f9a84","userequest_scroll_index.md":"63a279ee","userequest_throttle_index.md":"72165003","usescroll_index.md":"ea0696c9","usesessionstoragestate_index.md":"c6c9b95b","useset_index.md":"cc7344c0","usesize_index.md":"d3922935","usethrottle_index.md":"cabd86a8","usethrottlefn_index.md":"8b15aa2a","usetimeout_index.md":"2f042531","usetitle_index.md":"0ff812cc","usetoggle_index.md":"03ba73f4","usetrackedeffect_index.md":"cc4055dd","useupdate_index.md":"74e7614f","useurlstate_index.md":"be0c24ae","usevirtuallist_index.md":"6cc029f6","usewhydidyouupdate_index.md":"e8647289","usewinresize_index.md":"756e955e"}
