{"guide_index.md":"0ee1bf4d","index.md":"65776d02","useasyncorder_index.md":"3f232ef0","useboolean_index.md":"736ce3b7","usecookiestate_index.md":"7f283c14","usecounter_index.md":"ade60fa3","usedarkmode_index.md":"0cc2e4ba","usedebounce_index.md":"b3ef9f29","usedebouncefn_index.md":"bfc4e6ea","usedrop_index.md":"b4c40f2f","useeventemitter_index.md":"d6e38ab9","useeventlistener_index.md":"be505bae","useexternal_index.md":"fab1ef2a","usefavicon_index.md":"f66712b3","usefetchs_index.md":"7166c3bb","usefocuswithin_index.md":"eaad66d6","useformatresult_index.md":"616c5323","usefullscreen_index.md":"e6619b38","usehover_index.md":"c40ebf71","useinviewport_index.md":"28395a14","useinfinitescroll_index.md":"daa7645e","useinterval_index.md":"2224f2f8","usekeypress_index.md":"21557c51","uselocalstoragestate_index.md":"bb6e1d67","uselockfn_index.md":"4447c4d2","usemap_index.md":"ecc90d3e","usemedia_index.md":"ca367007","usemouse_index.md":"ddfae9b9","usenetwork_index.md":"e5417ca0","usepreview_index.md":"b3241ad2","userequest_basic_index.md":"37157677","userequest_cache_index.md":"b9052eac","userequest_debounce_index.md":"7af681a6","userequest_fetchs_index.md":"7f898fdf","userequest_guide_index.md":"158d19b9","userequest_index.md":"c34a0738","userequest_loadingdelay_index.md":"2a37a251","userequest_plugin_index.md":"3a99abb7","userequest_polling_index.md":"d010100e","userequest_ready_index.md":"a644980b","userequest_refreshdeps_index.md":"d4a7179d","userequest_refreshonwindowfocus_index.md":"815631d0","userequest_retry_index.md":"85fa9f67","userequest_scroll_index.md":"5cf82d6d","userequest_throttle_index.md":"ca4bb923","usescroll_index.md":"b827ecaf","usesessionstoragestate_index.md":"1f2b579e","useset_index.md":"ec6fc324","usesize_index.md":"c5e49b94","usethrottle_index.md":"a5b29bb2","usethrottlefn_index.md":"81ab6fe9","usetimeout_index.md":"a9444877","usetitle_index.md":"9a864b29","usetoggle_index.md":"308fa74b","usetrackedeffect_index.md":"cf5b7b06","useupdate_index.md":"388323a8","useurlstate_index.md":"85506544","usevirtuallist_index.md":"8c3efc22","usewhydidyouupdate_index.md":"6e7f48a0","usewinresize_index.md":"b5eafeb5"}
